botrun_llama_kb/__init__.py
botrun_llama_kb/adapters/__init__.py
botrun_llama_kb/adapters/file_source_adapter.py
botrun_llama_kb/adapters/local_directory_adapter.py
botrun_llama_kb/constants.py
botrun_llama_kb/knowledge_base_factory.py
botrun_llama_kb/knowledge_base_qdrant_store.py
botrun_llama_kb/knowledge_base_store.py
botrun_llama_kb-5.8.31.dist-info/METADATA
botrun_llama_kb-5.8.31.dist-info/WHEEL
botrun_llama_kb-5.8.31.dist-info/RECORD
