Metadata-Version: 2.3
Name: botrun-llama-kb
Version: 5.8.31
Summary: 
Author: sebastian-hsu
Author-email: sebastian.hsu@gmail.com
Requires-Python: >=3.11,<3.14
Classifier: Programming Language :: Python :: 3
Classifier: Programming Language :: Python :: 3.11
Classifier: Programming Language :: Python :: 3.12
Classifier: Programming Language :: Python :: 3.13
Provides-Extra: dev
Requires-Dist: botrun-llm-ranking (>=5.8.22,<6.0.0)
Requires-Dist: build (>=1.2.2.post1) ; extra == "dev"
Requires-Dist: fastembed (>=0.7.1,<0.8.0)
Requires-Dist: llama-index (>=0.13.0,<0.14.0)
Requires-Dist: llama-index-embeddings-google-genai (>=0.3.0,<0.4.0)
Requires-Dist: llama-index-llms-google-genai (>=0.3.0)
Requires-Dist: llama-index-multi-modal-llms-gemini (>=0.6.0,<0.7.0)
Requires-Dist: llama-index-vector-stores-qdrant (>=0.7.0,<0.8.0)
Requires-Dist: pydantic (>=2.11.7,<3.0.0)
Requires-Dist: pytest (>=8.4.1) ; extra == "dev"
Requires-Dist: pytest-asyncio (>=1.1.0) ; extra == "dev"
Requires-Dist: pytest-order (>=1.3.0) ; extra == "dev"
Requires-Dist: qdrant-client (>=1.15.0,<2.0.0)
Requires-Dist: twine (>=5.1.1) ; extra == "dev"
